travis/__init__.py
travis/__main__.py
travis/cli.py
travis/encrypt.py
travis/orderer.py
travis_encrypt-1.4.0.data/data/LICENSE
travis_encrypt-1.4.0.dist-info/LICENSE
travis_encrypt-1.4.0.dist-info/METADATA
travis_encrypt-1.4.0.dist-info/WHEEL
travis_encrypt-1.4.0.dist-info/entry_points.txt
travis_encrypt-1.4.0.dist-info/top_level.txt
travis_encrypt-1.4.0.dist-info/RECORD
