Metadata-Version: 2.1
Name: travis-encrypt
Version: 1.4.0
Summary: Encrypt passwords for use with Travis CI.
Home-page: https://github.com/mandeep/Travis-Encrypt
Author: Mandeep
Author-email: mandeep@keemail.me
License: MIT
Platform: UNKNOWN
Classifier: Development Status :: 5 - Production/Stable
Classifier: License :: OSI Approved :: MIT License
Classifier: Programming Language :: Python :: 2.7
Classifier: Programming Language :: Python :: 3.5
Classifier: Programming Language :: Python :: 3.6
Classifier: Programming Language :: Python :: 3.7
Classifier: Programming Language :: Python :: Implementation :: CPython
Classifier: Programming Language :: Python :: Implementation :: PyPy
Requires-Dist: click (>=7.0)
Requires-Dist: cryptography (>=2.6)
Requires-Dist: PyYAML (>=5.1)
Requires-Dist: requests (>=2.21)
Requires-Dist: pyperclip (==1.7)
Requires-Dist: python-dotenv (>=0.10)
